{
  "format_version": "1.13.0",
  "minecraft:feature_rules": {
    "description": {
      "identifier": "vp:vegetation_x_pond",
      "places_feature": "vp:vegetation_weight_x_pond"
    },
    "conditions": {
      "placement_pass": "underground_pass",
      "minecraft:biome_filter": [
        {
          "all_of": [
            {
              "test": "has_biome_tag",
              "operator": "!=",
              "value": "cold"
            },
            {
              "test": "has_biome_tag",
              "operator": "!=",
              "value": "extreme_hills"
            },
            {
              "any_of": [
                {
                  "test": "has_biome_tag",
                  "operator": "==",
                  "value": "plains"
                },
                {
                  "test": "has_biome_tag",
                  "operator": "==",
                  "value": "flower_forest"
                },
                {
                  "test": "has_biome_tag",
                  "operator": "==",
                  "value": "forest"
                },
                {
                  "test": "has_biome_tag",
                  "operator": "==",
                  "value": "swamp"
                },
                {
                  "test": "has_biome_tag",
                  "operator": "==",
                  "value": "swampland"
                },
                {
                  "test": "has_biome_tag",
                  "operator": "==",
                  "value": "mangrove_swamp"
                },
                {
                  "test": "has_biome_tag",
                  "operator": "==",
                  "value": "jungle"
                },
                {
                  "test": "has_biome_tag",
                  "operator": "==",
                  "value": "savanna"
                },
                {
                  "test": "has_biome_tag",
                  "operator": "==",
                  "value": "mooshroom_island"
                }
              ]
            }
          ]
        }
      ]
    },
    "distribution": {
      "iterations": 1,
      "scatter_chance": 5,
      "x": {
        "distribution": "uniform",
        "extent": [ 0, 16 ]
      },
      "y": "query.heightmap(variable.worldx, variable.worldz)",
      "z": {
        "distribution": "uniform",
        "extent": [ 0, 16 ]
      }
    }
  }
}